storynavigation/__init__.py
storynavigation/modules/actionanalysis.py
storynavigation/modules/actoranalysis.py
storynavigation/modules/constants.py
storynavigation/modules/error_handling.py
storynavigation/modules/meansanalysis.py
storynavigation/modules/purposeanalysis.py
storynavigation/modules/sentiment.py
storynavigation/modules/settinganalysis.py
storynavigation/modules/tagging.py
storynavigation/modules/util.py
storynavigation/resources/complete_data_columns.csv
storynavigation/resources/dutch_entities.csv
storynavigation/resources/dutch_halliday_action_list.csv
storynavigation/resources/dutch_prepositions.csv
storynavigation/resources/dutch_purpose_adverbs.csv
storynavigation/resources/dutch_purpose_verbs.csv
storynavigation/resources/dutch_time_words.csv
storynavigation/resources/dutch_verb_frames.csv
storynavigation/resources/dutchpronouns.txt
storynavigation/resources/dutchstopwords.txt
storynavigation/resources/english_entities.csv
storynavigation/resources/english_halliday_action_list.csv
storynavigation/resources/english_prepositions.csv
storynavigation/resources/english_time_words.csv
storynavigation/resources/english_verb_frames.csv
storynavigation/resources/englishpronouns.txt
storynavigation/resources/englishstopwords.txt
storynavigation/resources/false_positive_verbs_dutch.txt
storynavigation/resources/false_positive_verbs_english.txt
storynavigation/resources/past_tense_verbs_dutch.txt
storynavigation/resources/past_tense_verbs_english.txt
storynavigation/resources/present_tense_verbs_dutch.txt
storynavigation/resources/present_tense_verbs_english.txt
storynavigation/rules/multilingual_dsg_patterns_en.json
storynavigation/rules/multilingual_dsg_patterns_nl.json
storynavigation/widgets/OWSNActionAnalysis.py
storynavigation/widgets/OWSNActorAnalysis.py
storynavigation/widgets/OWSNMeansAnalysis.py
storynavigation/widgets/OWSNNarrativeNetwork.py
storynavigation/widgets/OWSNPurposeAnalysis.py
storynavigation/widgets/OWSNSentimentAnalyzer.py
storynavigator-0.1.1.dist-info/LICENSE
storynavigator-0.1.1.dist-info/METADATA
storynavigator-0.1.1.dist-info/WHEEL
storynavigator-0.1.1.dist-info/entry_points.txt
storynavigator-0.1.1.dist-info/top_level.txt
storynavigator-0.1.1.dist-info/RECORD
