Metadata-Version: 2.2
Name: storynavigator
Version: 0.1.1
Summary: Narrative analysis add-on for the Orange 3 data mining software package.
Author: Kody Moodley
License: GPL 3.0 or later
Project-URL: homepage, https://github.com/navigating-stories/orange-story-navigator
Project-URL: issues, https://github.com/navigating-stories/orange-story-navigator/issues
Project-URL: documentation, https://orange-story-navigator.readthedocs.io
Project-URL: changelog, https://github.com/navigating-stories/orange-story-navigator/releases
Keywords: orange3 add-on,story analysis,narrative theory,natural language processing,text mining,story networks,character networks
Classifier: Development Status :: 3 - Alpha
Classifier: Intended Audience :: Developers
Classifier: License :: OSI Approved :: GNU General Public License v3 or later (GPLv3+)
Classifier: Natural Language :: English
Classifier: Programming Language :: Python :: 3
Classifier: Programming Language :: Python :: 3.9
Classifier: Programming Language :: Python :: 3.10
Classifier: Programming Language :: Python :: 3.11
Requires-Python: >=3.9
License-File: LICENSE
Requires-Dist: pyqt6==6.7.1
Requires-Dist: pyqtwebengine==5.15.7
Requires-Dist: orange3==3.37
Requires-Dist: orange3-text==1.16.1
Requires-Dist: orange3-network==1.9.0
Requires-Dist: pandas==2.2.2
Requires-Dist: spacy==3.7.6
Requires-Dist: scipy==1.12.0
Requires-Dist: dhtmlparser3==3.0.17
Requires-Dist: nltk==3.9.1
Requires-Dist: textblob==0.18.0.post0
Requires-Dist: textblob-nl==0.0.1
Requires-Dist: pydot==3.0.1
Requires-Dist: graphviz==0.20.3
Requires-Dist: thefuzz==0.22.1
Requires-Dist: beautifulsoup4==4.12.3
Requires-Dist: transformers==4.44.2
Requires-Dist: torch==2.4.0
Requires-Dist: pytest==8.3.1
Provides-Extra: develop
Requires-Dist: bump-my-version; extra == "develop"
Requires-Dist: coverage; extra == "develop"
Requires-Dist: pytest; extra == "develop"
Requires-Dist: sphinx; extra == "develop"
Requires-Dist: sphinx_rtd_theme; extra == "develop"
Requires-Dist: sphinx-autoapi<=2.1.0; extra == "develop"
Requires-Dist: myst_parser; extra == "develop"
Requires-Dist: nbsphinx; extra == "develop"
Requires-Dist: black; extra == "develop"
Requires-Dist: pylint; extra == "develop"
Provides-Extra: publishing
Requires-Dist: twine; extra == "publishing"
Requires-Dist: wheel; extra == "publishing"
Requires-Dist: build; extra == "publishing"
